{
  "Standard Headhunting": {
    "Total Users": 1747,
    "Total Pulls": 185560,
    "Oroberyl Spent": 92780000,
    "6-Star": {
      "Rate": "1.575%",
      "Count": 2922,
      "Median Pity": 59,
      "Won": null
    },
    "5-Star": {
      "Rate": "13.336%",
      "Count": 24747
    }
  },
  "Special Headhunting": {
    "Hues Of Passion": {
      "Total Users": 540,
      "Total Pulls": 34199,
      "Oroberyl Spent": 17099500,
      "6-Star": {
        "Rate": "1.842%",
        "Count": 630,
        "Median Pity": 23,
        "Won": "52%"
      },
      "5-Star": {
        "Rate": "11.831%",
        "Count": 4046
      },
      "Total Obtained": 370,
      "Featured 6-Star %": "1.842%",
      "Featured Image": "https://goyfield.moe/images/operators/preview/yvonne.png"
    },
    "The Floaty Messenger": {
      "Total Users": 1705,
      "Total Pulls": 138222,
      "Oroberyl Spent": 69111000,
      "6-Star": {
        "Rate": "1.901%",
        "Count": 2628,
        "Median Pity": 30,
        "Won": "49%"
      },
      "5-Star": {
        "Rate": "12.340%",
        "Count": 17056
      },
      "Total Obtained": 30,
      "Featured 6-Star %": "1.901%",
      "Featured Image": "https://goyfield.moe/images/operators/preview/gilberta.png"
    },
    "Scars Of The Forge": {
      "Total Users": 1674,
      "Total Pulls": 177846,
      "Oroberyl Spent": 88923000,
      "6-Star": {
        "Rate": "1.744%",
        "Count": 3101,
        "Median Pity": 44,
        "Won": "52%"
      },
      "5-Star": {
        "Rate": "12.519%",
        "Count": 22264
      },
      "Total Obtained": 44,
      "Featured 6-Star %": "1.744%",
      "Featured Image": "https://goyfield.moe/images/operators/preview/laevatain.png"
    }
  },
  "Event Weapon": {
    "Graffiti Issue": {
      "Total Users": 328,
      "Total Pulls": 14600,
      "Oroberyl Spent": null,
      "6-Star": {
        "Rate": "5.370%",
        "Count": 784,
        "Median Pity": 12,
        "Won": "5%"
      },
      "5-Star": {
        "Rate": "17.288%",
        "Count": 2524
      },
      "Total Obtained": 236,
      "Featured 6-Star %": "5.370%",
      "Featured Image": "https://goyfield.moe/images/weapons/artzyTyrannical.png"
    },
    "Express Delivery Issue": {
      "Total Users": 1068,
      "Total Pulls": 48315,
      "Oroberyl Spent": null,
      "6-Star": {
        "Rate": "4.963%",
        "Count": 2398,
        "Median Pity": 13,
        "Won": "27%"
      },
      "5-Star": {
        "Rate": "17.080%",
        "Count": 8252
      },
      "Total Obtained": 788,
      "Featured 6-Star %": "4.963%",
      "Featured Image": "https://goyfield.moe/images/weapons/deliveryGuaranteed.png"
    },
    "Smelting Forge Issue": {
      "Total Users": 1408,
      "Total Pulls": 96350,
      "Oroberyl Spent": null,
      "6-Star": {
        "Rate": "5.216%",
        "Count": 5026,
        "Median Pity": 14,
        "Won": "25%"
      },
      "5-Star": {
        "Rate": "17.285%",
        "Count": 16654
      },
      "Total Obtained": 14,
      "Featured 6-Star %": "5.216%",
      "Featured Image": "https://goyfield.moe/images/weapons/forgebornScathe.png"
    }
  },
  "Standard Weapon": {
    "Solid Ice Issue": {
      "Total Users": 557,
      "Total Pulls": 22170,
      "Oroberyl Spent": null,
      "6-Star": {
        "Rate": "4.926%",
        "Count": 1092,
        "Median Pity": 13,
        "Won": "28%"
      },
      "5-Star": {
        "Rate": "16.978%",
        "Count": 3764
      },
      "Total Obtained": 369,
      "Featured 6-Star %": "4.926%",
      "Featured Image": "https://goyfield.moe/images/weapons/khravengger.png"
    },
    "Cosmic Voice Issue": {
      "Total Users": 1618,
      "Total Pulls": 20255,
      "Oroberyl Spent": null,
      "6-Star": {
        "Rate": "4.236%",
        "Count": 858,
        "Median Pity": 5,
        "Won": "24%"
      },
      "5-Star": {
        "Rate": "16.746%",
        "Count": 3392
      },
      "Total Obtained": 213,
      "Featured 6-Star %": "4.236%",
      "Featured Image": "https://goyfield.moe/images/weapons/dreamsOfTheStarryBeach.png"
    },
    "Far Expedition Issue": {
      "Total Users": 502,
      "Total Pulls": 20095,
      "Oroberyl Spent": null,
      "6-Star": {
        "Rate": "4.812%",
        "Count": 967,
        "Median Pity": 13,
        "Won": "28%"
      },
      "5-Star": {
        "Rate": "16.661%",
        "Count": 3348
      },
      "Total Obtained": 317,
      "Featured 6-Star %": "4.812%",
      "Featured Image": "https://goyfield.moe/images/weapons/neverRest.png"
    },
    "Rising Mount Issue": {
      "Total Users": 186,
      "Total Pulls": 6675,
      "Oroberyl Spent": null,
      "6-Star": {
        "Rate": "4.974%",
        "Count": 332,
        "Median Pity": 11,
        "Won": "22%"
      },
      "5-Star": {
        "Rate": "16.524%",
        "Count": 1103
      },
      "Total Obtained": 90,
      "Featured 6-Star %": "4.974%",
      "Featured Image": "https://goyfield.moe/images/weapons/mountainBearer.png"
    },
    "Thunderous Peal Issue": {
      "Total Users": 140,
      "Total Pulls": 5020,
      "Oroberyl Spent": null,
      "6-Star": {
        "Rate": "4.681%",
        "Count": 235,
        "Median Pity": 12,
        "Won": "25%"
      },
      "5-Star": {
        "Rate": "16.594%",
        "Count": 833
      },
      "Total Obtained": 72,
      "Featured 6-Star %": "4.681%",
      "Featured Image": "https://goyfield.moe/images/weapons/thunderberge.png"
    }
  }
}