{
  "Standard Headhunting": {
    "Total Users": 2325,
    "Total Pulls": 253069,
    "Oroberyl Spent": 126534500,
    "6-Star": {
      "Rate": "1.564%",
      "Count": 3959,
      "Median Pity": 59,
      "Won": null
    },
    "5-Star": {
      "Rate": "13.348%",
      "Count": 33779
    }
  },
  "Special Headhunting": {
    "River's Daughter": {
      "Total Users": 426,
      "Total Pulls": 32459,
      "Oroberyl Spent": 16229500,
      "6-Star": {
        "Rate": "1.962%",
        "Count": 637,
        "Median Pity": 29,
        "Won": "49%"
      },
      "5-Star": {
        "Rate": "11.713%",
        "Count": 3802
      },
      "Total Obtained": 364,
      "Featured 6-Star %": "1.962%",
      "Featured Image": "https://goyfield.moe/images/operators/preview/tangtang.png"
    },
    "Hues Of Passion": {
      "Total Users": 1241,
      "Total Pulls": 80876,
      "Oroberyl Spent": 40438000,
      "6-Star": {
        "Rate": "1.746%",
        "Count": 1412,
        "Median Pity": 25,
        "Won": "52%"
      },
      "5-Star": {
        "Rate": "11.876%",
        "Count": 9605
      },
      "Total Obtained": 835,
      "Featured 6-Star %": "1.746%",
      "Featured Image": "https://goyfield.moe/images/operators/preview/yvonne.png"
    },
    "The Floaty Messenger": {
      "Total Users": 2261,
      "Total Pulls": 184172,
      "Oroberyl Spent": 92086000,
      "6-Star": {
        "Rate": "1.853%",
        "Count": 3413,
        "Median Pity": 30,
        "Won": "50%"
      },
      "5-Star": {
        "Rate": "12.179%",
        "Count": 22430
      },
      "Total Obtained": 30,
      "Featured 6-Star %": "1.853%",
      "Featured Image": "https://goyfield.moe/images/operators/preview/gilberta.png"
    },
    "Scars Of The Forge": {
      "Total Users": 2208,
      "Total Pulls": 228729,
      "Oroberyl Spent": 114364500,
      "6-Star": {
        "Rate": "1.723%",
        "Count": 3942,
        "Median Pity": 45,
        "Won": "52%"
      },
      "5-Star": {
        "Rate": "12.395%",
        "Count": 28352
      },
      "Total Obtained": 45,
      "Featured 6-Star %": "1.723%",
      "Featured Image": "https://goyfield.moe/images/operators/preview/laevatain.png"
    }
  },
  "Event Weapon": {
    "Brigand's Calling": {
      "Total Users": 256,
      "Total Pulls": 11190,
      "Oroberyl Spent": null,
      "6-Star": {
        "Rate": "5.264%",
        "Count": 589,
        "Median Pity": 12,
        "Won": "26%"
      },
      "5-Star": {
        "Rate": "16.801%",
        "Count": 1880
      },
      "Total Obtained": 181,
      "Featured 6-Star %": "5.264%",
      "Featured Image": "https://goyfield.moe/images/weapons/brigandsCalling.png"
    },
    "Graffiti Issue": {
      "Total Users": 708,
      "Total Pulls": 32780,
      "Oroberyl Spent": null,
      "6-Star": {
        "Rate": "5.177%",
        "Count": 1697,
        "Median Pity": 13,
        "Won": "18%"
      },
      "5-Star": {
        "Rate": "17.117%",
        "Count": 5611
      },
      "Total Obtained": 529,
      "Featured 6-Star %": "5.177%",
      "Featured Image": "https://goyfield.moe/images/weapons/artzyTyrannical.png"
    },
    "Express Delivery Issue": {
      "Total Users": 1464,
      "Total Pulls": 67970,
      "Oroberyl Spent": null,
      "6-Star": {
        "Rate": "5.021%",
        "Count": 3413,
        "Median Pity": 13,
        "Won": "26%"
      },
      "5-Star": {
        "Rate": "17.088%",
        "Count": 11615
      },
      "Total Obtained": 13,
      "Featured 6-Star %": "5.021%",
      "Featured Image": "https://goyfield.moe/images/weapons/deliveryGuaranteed.png"
    },
    "Smelting Forge Issue": {
      "Total Users": 1854,
      "Total Pulls": 126040,
      "Oroberyl Spent": null,
      "6-Star": {
        "Rate": "5.253%",
        "Count": 6621,
        "Median Pity": 14,
        "Won": "25%"
      },
      "5-Star": {
        "Rate": "17.185%",
        "Count": 21660
      },
      "Total Obtained": 14,
      "Featured 6-Star %": "5.253%",
      "Featured Image": "https://goyfield.moe/images/weapons/forgebornScathe.png"
    }
  },
  "Standard Weapon": {
    "Solid Ice Issue": {
      "Total Users": 785,
      "Total Pulls": 31570,
      "Oroberyl Spent": null,
      "6-Star": {
        "Rate": "4.976%",
        "Count": 1571,
        "Median Pity": 13,
        "Won": "28%"
      },
      "5-Star": {
        "Rate": "16.918%",
        "Count": 5341
      },
      "Total Obtained": 533,
      "Featured 6-Star %": "4.976%",
      "Featured Image": "https://goyfield.moe/images/weapons/khravengger.png"
    },
    "Cosmic Voice Issue": {
      "Total Users": 2168,
      "Total Pulls": 27355,
      "Oroberyl Spent": null,
      "6-Star": {
        "Rate": "4.189%",
        "Count": 1146,
        "Median Pity": 5,
        "Won": "24%"
      },
      "5-Star": {
        "Rate": "16.655%",
        "Count": 4556
      },
      "Total Obtained": 291,
      "Featured 6-Star %": "4.189%",
      "Featured Image": "https://goyfield.moe/images/weapons/dreamsOfTheStarryBeach.png"
    },
    "Far Expedition Issue": {
      "Total Users": 679,
      "Total Pulls": 27785,
      "Oroberyl Spent": null,
      "6-Star": {
        "Rate": "4.877%",
        "Count": 1355,
        "Median Pity": 12,
        "Won": "27%"
      },
      "5-Star": {
        "Rate": "16.692%",
        "Count": 4638
      },
      "Total Obtained": 436,
      "Featured 6-Star %": "4.877%",
      "Featured Image": "https://goyfield.moe/images/weapons/neverRest.png"
    },
    "Rising Mount Issue": {
      "Total Users": 267,
      "Total Pulls": 9705,
      "Oroberyl Spent": null,
      "6-Star": {
        "Rate": "4.956%",
        "Count": 481,
        "Median Pity": 12,
        "Won": "22%"
      },
      "5-Star": {
        "Rate": "16.765%",
        "Count": 1627
      },
      "Total Obtained": 133,
      "Featured 6-Star %": "4.956%",
      "Featured Image": "https://goyfield.moe/images/weapons/mountainBearer.png"
    },
    "Thunderous Peal Issue": {
      "Total Users": 191,
      "Total Pulls": 6930,
      "Oroberyl Spent": null,
      "6-Star": {
        "Rate": "4.531%",
        "Count": 314,
        "Median Pity": 12,
        "Won": "24%"
      },
      "5-Star": {
        "Rate": "16.436%",
        "Count": 1139
      },
      "Total Obtained": 95,
      "Featured 6-Star %": "4.531%",
      "Featured Image": "https://goyfield.moe/images/weapons/thunderberge.png"
    }
  }
}