{
  "Standard Headhunting": {
    "Total Users": 1998,
    "Total Pulls": 213187,
    "Oroberyl Spent": 106593500,
    "6-Star": {
      "Rate": "1.572%",
      "Count": 3351,
      "Median Pity": 59,
      "Won": null
    },
    "5-Star": {
      "Rate": "13.320%",
      "Count": 28397
    }
  },
  "Special Headhunting": {
    "Hues Of Passion": {
      "Total Users": 887,
      "Total Pulls": 58013,
      "Oroberyl Spent": 29006500,
      "6-Star": {
        "Rate": "1.806%",
        "Count": 1048,
        "Median Pity": 24,
        "Won": "54%"
      },
      "5-Star": {
        "Rate": "11.765%",
        "Count": 6825
      },
      "Total Obtained": 631,
      "Featured 6-Star %": "1.806%",
      "Featured Image": "https://goyfield.moe/images/operators/preview/yvonne.png"
    },
    "The Floaty Messenger": {
      "Total Users": 1947,
      "Total Pulls": 157944,
      "Oroberyl Spent": 78972000,
      "6-Star": {
        "Rate": "1.879%",
        "Count": 2968,
        "Median Pity": 30,
        "Won": "50%"
      },
      "5-Star": {
        "Rate": "12.266%",
        "Count": 19373
      },
      "Total Obtained": 30,
      "Featured 6-Star %": "1.879%",
      "Featured Image": "https://goyfield.moe/images/operators/preview/gilberta.png"
    },
    "Scars Of The Forge": {
      "Total Users": 1901,
      "Total Pulls": 199638,
      "Oroberyl Spent": 99819000,
      "6-Star": {
        "Rate": "1.734%",
        "Count": 3462,
        "Median Pity": 44,
        "Won": "51%"
      },
      "5-Star": {
        "Rate": "12.469%",
        "Count": 24893
      },
      "Total Obtained": 44,
      "Featured 6-Star %": "1.734%",
      "Featured Image": "https://goyfield.moe/images/operators/preview/laevatain.png"
    }
  },
  "Event Weapon": {
    "Graffiti Issue": {
      "Total Users": 513,
      "Total Pulls": 22855,
      "Oroberyl Spent": null,
      "6-Star": {
        "Rate": "5.141%",
        "Count": 1175,
        "Median Pity": 13,
        "Won": "14%"
      },
      "5-Star": {
        "Rate": "17.173%",
        "Count": 3925
      },
      "Total Obtained": 365,
      "Featured 6-Star %": "5.141%",
      "Featured Image": "https://goyfield.moe/images/weapons/artzyTyrannical.png"
    },
    "Express Delivery Issue": {
      "Total Users": 1237,
      "Total Pulls": 56450,
      "Oroberyl Spent": null,
      "6-Star": {
        "Rate": "4.971%",
        "Count": 2806,
        "Median Pity": 13,
        "Won": "26%"
      },
      "5-Star": {
        "Rate": "17.095%",
        "Count": 9650
      },
      "Total Obtained": 914,
      "Featured 6-Star %": "4.971%",
      "Featured Image": "https://goyfield.moe/images/weapons/deliveryGuaranteed.png"
    },
    "Smelting Forge Issue": {
      "Total Users": 1594,
      "Total Pulls": 109410,
      "Oroberyl Spent": null,
      "6-Star": {
        "Rate": "5.239%",
        "Count": 5732,
        "Median Pity": 14,
        "Won": "25%"
      },
      "5-Star": {
        "Rate": "17.241%",
        "Count": 18863
      },
      "Total Obtained": 14,
      "Featured 6-Star %": "5.239%",
      "Featured Image": "https://goyfield.moe/images/weapons/forgebornScathe.png"
    }
  },
  "Standard Weapon": {
    "Solid Ice Issue": {
      "Total Users": 654,
      "Total Pulls": 25880,
      "Oroberyl Spent": null,
      "6-Star": {
        "Rate": "4.919%",
        "Count": 1273,
        "Median Pity": 13,
        "Won": "28%"
      },
      "5-Star": {
        "Rate": "16.843%",
        "Count": 4359
      },
      "Total Obtained": 433,
      "Featured 6-Star %": "4.919%",
      "Featured Image": "https://goyfield.moe/images/weapons/khravengger.png"
    },
    "Cosmic Voice Issue": {
      "Total Users": 1857,
      "Total Pulls": 23205,
      "Oroberyl Spent": null,
      "6-Star": {
        "Rate": "4.150%",
        "Count": 963,
        "Median Pity": 5,
        "Won": "24%"
      },
      "5-Star": {
        "Rate": "16.729%",
        "Count": 3882
      },
      "Total Obtained": 243,
      "Featured 6-Star %": "4.150%",
      "Featured Image": "https://goyfield.moe/images/weapons/dreamsOfTheStarryBeach.png"
    },
    "Far Expedition Issue": {
      "Total Users": 585,
      "Total Pulls": 23565,
      "Oroberyl Spent": null,
      "6-Star": {
        "Rate": "4.838%",
        "Count": 1140,
        "Median Pity": 13,
        "Won": "28%"
      },
      "5-Star": {
        "Rate": "16.618%",
        "Count": 3916
      },
      "Total Obtained": 371,
      "Featured 6-Star %": "4.838%",
      "Featured Image": "https://goyfield.moe/images/weapons/neverRest.png"
    },
    "Rising Mount Issue": {
      "Total Users": 224,
      "Total Pulls": 7915,
      "Oroberyl Spent": null,
      "6-Star": {
        "Rate": "4.877%",
        "Count": 386,
        "Median Pity": 12,
        "Won": "22%"
      },
      "5-Star": {
        "Rate": "16.513%",
        "Count": 1307
      },
      "Total Obtained": 106,
      "Featured 6-Star %": "4.877%",
      "Featured Image": "https://goyfield.moe/images/weapons/mountainBearer.png"
    },
    "Thunderous Peal Issue": {
      "Total Users": 163,
      "Total Pulls": 5850,
      "Oroberyl Spent": null,
      "6-Star": {
        "Rate": "4.615%",
        "Count": 270,
        "Median Pity": 12,
        "Won": "24%"
      },
      "5-Star": {
        "Rate": "16.462%",
        "Count": 963
      },
      "Total Obtained": 80,
      "Featured 6-Star %": "4.615%",
      "Featured Image": "https://goyfield.moe/images/weapons/thunderberge.png"
    }
  }
}