{
  "Standard Headhunting": {
    "Total Users": 2104,
    "Total Pulls": 225595,
    "Oroberyl Spent": 112797500,
    "6-Star": {
      "Rate": "1.575%",
      "Count": 3554,
      "Median Pity": 59,
      "Won": null
    },
    "5-Star": {
      "Rate": "13.327%",
      "Count": 30066
    }
  },
  "Special Headhunting": {
    "River's Daughter": {
      "Total Users": 130,
      "Total Pulls": 7782,
      "Oroberyl Spent": 3891000,
      "6-Star": {
        "Rate": "2.043%",
        "Count": 159,
        "Median Pity": 20,
        "Won": "55%"
      },
      "5-Star": {
        "Rate": "11.115%",
        "Count": 865
      },
      "Total Obtained": 96,
      "Featured 6-Star %": "2.043%",
      "Featured Image": "https://goyfield.moe/images/operators/preview/tangtang.png"
    },
    "Hues Of Passion": {
      "Total Users": 1005,
      "Total Pulls": 65479,
      "Oroberyl Spent": 32739500,
      "6-Star": {
        "Rate": "1.772%",
        "Count": 1160,
        "Median Pity": 25,
        "Won": "54%"
      },
      "5-Star": {
        "Rate": "11.818%",
        "Count": 7738
      },
      "Total Obtained": 698,
      "Featured 6-Star %": "1.772%",
      "Featured Image": "https://goyfield.moe/images/operators/preview/yvonne.png"
    },
    "The Floaty Messenger": {
      "Total Users": 2049,
      "Total Pulls": 166735,
      "Oroberyl Spent": 83367500,
      "6-Star": {
        "Rate": "1.870%",
        "Count": 3118,
        "Median Pity": 30,
        "Won": "50%"
      },
      "5-Star": {
        "Rate": "12.221%",
        "Count": 20376
      },
      "Total Obtained": 30,
      "Featured 6-Star %": "1.870%",
      "Featured Image": "https://goyfield.moe/images/operators/preview/gilberta.png"
    },
    "Scars Of The Forge": {
      "Total Users": 2002,
      "Total Pulls": 208745,
      "Oroberyl Spent": 104372500,
      "6-Star": {
        "Rate": "1.731%",
        "Count": 3614,
        "Median Pity": 44,
        "Won": "52%"
      },
      "5-Star": {
        "Rate": "12.453%",
        "Count": 25994
      },
      "Total Obtained": 44,
      "Featured 6-Star %": "1.731%",
      "Featured Image": "https://goyfield.moe/images/operators/preview/laevatain.png"
    }
  },
  "Event Weapon": {
    "Brigand's Calling": {
      "Total Users": 64,
      "Total Pulls": 2600,
      "Oroberyl Spent": null,
      "6-Star": {
        "Rate": "5.577%",
        "Count": 145,
        "Median Pity": 11,
        "Won": "31%"
      },
      "5-Star": {
        "Rate": "16.846%",
        "Count": 438
      },
      "Total Obtained": 50,
      "Featured 6-Star %": "5.577%",
      "Featured Image": "https://goyfield.moe/images/weapons/brigandsCalling.png"
    },
    "Graffiti Issue": {
      "Total Users": 569,
      "Total Pulls": 25625,
      "Oroberyl Spent": null,
      "6-Star": {
        "Rate": "5.163%",
        "Count": 1323,
        "Median Pity": 13,
        "Won": "15%"
      },
      "5-Star": {
        "Rate": "17.085%",
        "Count": 4378
      },
      "Total Obtained": 413,
      "Featured 6-Star %": "5.163%",
      "Featured Image": "https://goyfield.moe/images/weapons/artzyTyrannical.png"
    },
    "Express Delivery Issue": {
      "Total Users": 1302,
      "Total Pulls": 59900,
      "Oroberyl Spent": null,
      "6-Star": {
        "Rate": "5.015%",
        "Count": 3004,
        "Median Pity": 13,
        "Won": "26%"
      },
      "5-Star": {
        "Rate": "17.083%",
        "Count": 10233
      },
      "Total Obtained": 984,
      "Featured 6-Star %": "5.015%",
      "Featured Image": "https://goyfield.moe/images/weapons/deliveryGuaranteed.png"
    },
    "Smelting Forge Issue": {
      "Total Users": 1678,
      "Total Pulls": 115000,
      "Oroberyl Spent": null,
      "6-Star": {
        "Rate": "5.235%",
        "Count": 6020,
        "Median Pity": 14,
        "Won": "25%"
      },
      "5-Star": {
        "Rate": "17.222%",
        "Count": 19805
      },
      "Total Obtained": 14,
      "Featured 6-Star %": "5.235%",
      "Featured Image": "https://goyfield.moe/images/weapons/forgebornScathe.png"
    }
  },
  "Standard Weapon": {
    "Solid Ice Issue": {
      "Total Users": 689,
      "Total Pulls": 27460,
      "Oroberyl Spent": null,
      "6-Star": {
        "Rate": "4.927%",
        "Count": 1353,
        "Median Pity": 13,
        "Won": "28%"
      },
      "5-Star": {
        "Rate": "16.956%",
        "Count": 4656
      },
      "Total Obtained": 457,
      "Featured 6-Star %": "4.927%",
      "Featured Image": "https://goyfield.moe/images/weapons/khravengger.png"
    },
    "Cosmic Voice Issue": {
      "Total Users": 1957,
      "Total Pulls": 24495,
      "Oroberyl Spent": null,
      "6-Star": {
        "Rate": "4.095%",
        "Count": 1003,
        "Median Pity": 5,
        "Won": "24%"
      },
      "5-Star": {
        "Rate": "16.775%",
        "Count": 4109
      },
      "Total Obtained": 254,
      "Featured 6-Star %": "4.095%",
      "Featured Image": "https://goyfield.moe/images/weapons/dreamsOfTheStarryBeach.png"
    },
    "Far Expedition Issue": {
      "Total Users": 617,
      "Total Pulls": 24995,
      "Oroberyl Spent": null,
      "6-Star": {
        "Rate": "4.845%",
        "Count": 1211,
        "Median Pity": 13,
        "Won": "27%"
      },
      "5-Star": {
        "Rate": "16.583%",
        "Count": 4145
      },
      "Total Obtained": 390,
      "Featured 6-Star %": "4.845%",
      "Featured Image": "https://goyfield.moe/images/weapons/neverRest.png"
    },
    "Rising Mount Issue": {
      "Total Users": 240,
      "Total Pulls": 8645,
      "Oroberyl Spent": null,
      "6-Star": {
        "Rate": "4.928%",
        "Count": 426,
        "Median Pity": 12,
        "Won": "22%"
      },
      "5-Star": {
        "Rate": "16.472%",
        "Count": 1424
      },
      "Total Obtained": 117,
      "Featured 6-Star %": "4.928%",
      "Featured Image": "https://goyfield.moe/images/weapons/mountainBearer.png"
    },
    "Thunderous Peal Issue": {
      "Total Users": 171,
      "Total Pulls": 6250,
      "Oroberyl Spent": null,
      "6-Star": {
        "Rate": "4.672%",
        "Count": 292,
        "Median Pity": 12,
        "Won": "23%"
      },
      "5-Star": {
        "Rate": "16.368%",
        "Count": 1023
      },
      "Total Obtained": 86,
      "Featured 6-Star %": "4.672%",
      "Featured Image": "https://goyfield.moe/images/weapons/thunderberge.png"
    }
  }
}