{
  "Standard Headhunting": {
    "Total Users": 2238,
    "Total Pulls": 242121,
    "Oroberyl Spent": 121060500,
    "6-Star": {
      "Rate": "1.566%",
      "Count": 3792,
      "Median Pity": 60,
      "Won": null
    },
    "5-Star": {
      "Rate": "13.332%",
      "Count": 32280
    }
  },
  "Special Headhunting": {
    "River's Daughter": {
      "Total Users": 317,
      "Total Pulls": 23735,
      "Oroberyl Spent": 11867500,
      "6-Star": {
        "Rate": "1.984%",
        "Count": 471,
        "Median Pity": 28,
        "Won": "50%"
      },
      "5-Star": {
        "Rate": "11.637%",
        "Count": 2762
      },
      "Total Obtained": 272,
      "Featured 6-Star %": "1.984%",
      "Featured Image": "https://goyfield.moe/images/operators/preview/tangtang.png"
    },
    "Hues Of Passion": {
      "Total Users": 1154,
      "Total Pulls": 74989,
      "Oroberyl Spent": 37494500,
      "6-Star": {
        "Rate": "1.751%",
        "Count": 1313,
        "Median Pity": 25,
        "Won": "53%"
      },
      "5-Star": {
        "Rate": "11.872%",
        "Count": 8903
      },
      "Total Obtained": 782,
      "Featured 6-Star %": "1.751%",
      "Featured Image": "https://goyfield.moe/images/operators/preview/yvonne.png"
    },
    "The Floaty Messenger": {
      "Total Users": 2180,
      "Total Pulls": 177241,
      "Oroberyl Spent": 88620500,
      "6-Star": {
        "Rate": "1.858%",
        "Count": 3293,
        "Median Pity": 30,
        "Won": "50%"
      },
      "5-Star": {
        "Rate": "12.204%",
        "Count": 21630
      },
      "Total Obtained": 30,
      "Featured 6-Star %": "1.858%",
      "Featured Image": "https://goyfield.moe/images/operators/preview/gilberta.png"
    },
    "Scars Of The Forge": {
      "Total Users": 2127,
      "Total Pulls": 220810,
      "Oroberyl Spent": 110405000,
      "6-Star": {
        "Rate": "1.723%",
        "Count": 3805,
        "Median Pity": 45,
        "Won": "52%"
      },
      "5-Star": {
        "Rate": "12.419%",
        "Count": 27422
      },
      "Total Obtained": 45,
      "Featured 6-Star %": "1.723%",
      "Featured Image": "https://goyfield.moe/images/operators/preview/laevatain.png"
    }
  },
  "Event Weapon": {
    "Brigand's Calling": {
      "Total Users": 192,
      "Total Pulls": 8460,
      "Oroberyl Spent": null,
      "6-Star": {
        "Rate": "5.343%",
        "Count": 452,
        "Median Pity": 12,
        "Won": "26%"
      },
      "5-Star": {
        "Rate": "17.033%",
        "Count": 1441
      },
      "Total Obtained": 139,
      "Featured 6-Star %": "5.343%",
      "Featured Image": "https://goyfield.moe/images/weapons/brigandsCalling.png"
    },
    "Graffiti Issue": {
      "Total Users": 651,
      "Total Pulls": 29820,
      "Oroberyl Spent": null,
      "6-Star": {
        "Rate": "5.171%",
        "Count": 1542,
        "Median Pity": 13,
        "Won": "17%"
      },
      "5-Star": {
        "Rate": "17.136%",
        "Count": 5110
      },
      "Total Obtained": 475,
      "Featured 6-Star %": "5.171%",
      "Featured Image": "https://goyfield.moe/images/weapons/artzyTyrannical.png"
    },
    "Express Delivery Issue": {
      "Total Users": 1402,
      "Total Pulls": 65080,
      "Oroberyl Spent": null,
      "6-Star": {
        "Rate": "5.018%",
        "Count": 3266,
        "Median Pity": 14,
        "Won": "26%"
      },
      "5-Star": {
        "Rate": "17.111%",
        "Count": 11136
      },
      "Total Obtained": 14,
      "Featured 6-Star %": "5.018%",
      "Featured Image": "https://goyfield.moe/images/weapons/deliveryGuaranteed.png"
    },
    "Smelting Forge Issue": {
      "Total Users": 1784,
      "Total Pulls": 121280,
      "Oroberyl Spent": null,
      "6-Star": {
        "Rate": "5.252%",
        "Count": 6370,
        "Median Pity": 14,
        "Won": "25%"
      },
      "5-Star": {
        "Rate": "17.197%",
        "Count": 20856
      },
      "Total Obtained": 14,
      "Featured 6-Star %": "5.252%",
      "Featured Image": "https://goyfield.moe/images/weapons/forgebornScathe.png"
    }
  },
  "Standard Weapon": {
    "Solid Ice Issue": {
      "Total Users": 750,
      "Total Pulls": 30260,
      "Oroberyl Spent": null,
      "6-Star": {
        "Rate": "4.983%",
        "Count": 1508,
        "Median Pity": 13,
        "Won": "28%"
      },
      "5-Star": {
        "Rate": "16.907%",
        "Count": 5116
      },
      "Total Obtained": 509,
      "Featured 6-Star %": "4.983%",
      "Featured Image": "https://goyfield.moe/images/weapons/khravengger.png"
    },
    "Cosmic Voice Issue": {
      "Total Users": 2085,
      "Total Pulls": 26265,
      "Oroberyl Spent": null,
      "6-Star": {
        "Rate": "4.200%",
        "Count": 1103,
        "Median Pity": 5,
        "Won": "24%"
      },
      "5-Star": {
        "Rate": "16.665%",
        "Count": 4377
      },
      "Total Obtained": 279,
      "Featured 6-Star %": "4.200%",
      "Featured Image": "https://goyfield.moe/images/weapons/dreamsOfTheStarryBeach.png"
    },
    "Far Expedition Issue": {
      "Total Users": 654,
      "Total Pulls": 26655,
      "Oroberyl Spent": null,
      "6-Star": {
        "Rate": "4.847%",
        "Count": 1292,
        "Median Pity": 13,
        "Won": "27%"
      },
      "5-Star": {
        "Rate": "16.657%",
        "Count": 4440
      },
      "Total Obtained": 416,
      "Featured 6-Star %": "4.847%",
      "Featured Image": "https://goyfield.moe/images/weapons/neverRest.png"
    },
    "Rising Mount Issue": {
      "Total Users": 257,
      "Total Pulls": 9335,
      "Oroberyl Spent": null,
      "6-Star": {
        "Rate": "4.906%",
        "Count": 458,
        "Median Pity": 12,
        "Won": "22%"
      },
      "5-Star": {
        "Rate": "16.733%",
        "Count": 1562
      },
      "Total Obtained": 127,
      "Featured 6-Star %": "4.906%",
      "Featured Image": "https://goyfield.moe/images/weapons/mountainBearer.png"
    },
    "Thunderous Peal Issue": {
      "Total Users": 186,
      "Total Pulls": 6710,
      "Oroberyl Spent": null,
      "6-Star": {
        "Rate": "4.560%",
        "Count": 306,
        "Median Pity": 12,
        "Won": "24%"
      },
      "5-Star": {
        "Rate": "16.423%",
        "Count": 1102
      },
      "Total Obtained": 94,
      "Featured 6-Star %": "4.560%",
      "Featured Image": "https://goyfield.moe/images/weapons/thunderberge.png"
    }
  }
}